MANIFEST.in
README.rst
setup.py
django_paginationlinks.egg-info/PKG-INFO
django_paginationlinks.egg-info/SOURCES.txt
django_paginationlinks.egg-info/dependency_links.txt
django_paginationlinks.egg-info/top_level.txt
paginationlinks/__init__.py
paginationlinks/templatetags/__init__.py
paginationlinks/templatetags/pagination_links.py