Metadata-Version: 1.1
Name: django-paginationlinks
Version: 0.1
Summary: Django Pagination Links
Home-page: https://github.com/blancltd/django-paginationlinks
Author: Alex Tomkins
Author-email: alex@blanc.ltd.uk
License: BSD
Platform: any
Classifier: Environment :: Web Environment
Classifier: Framework :: Django
Classifier: License :: OSI Approved :: BSD License
Classifier: Operating System :: OS Independent
Classifier: Programming Language :: Python
Classifier: Programming Language :: Python :: 2
Classifier: Programming Language :: Python :: 2.7
Classifier: Programming Language :: Python :: 3
Classifier: Programming Language :: Python :: 3.2
Classifier: Programming Language :: Python :: 3.3
